plantuml/__init__.py
plantuml/macro.py
TracPlantUml-2.3.dist-info/COPYING
TracPlantUml-2.3.dist-info/METADATA
TracPlantUml-2.3.dist-info/WHEEL
TracPlantUml-2.3.dist-info/entry_points.txt
TracPlantUml-2.3.dist-info/top_level.txt
TracPlantUml-2.3.dist-info/RECORD
